gitguardian/__init__.py
gitguardian/sdk.py
gitguardian/hooks/__init__.py
gitguardian/hooks/hook.py
gitguardian/models/__init__.py
gitguardian/models/accept_team_request_request.py
gitguardian/models/api_token_details.py
gitguardian/models/api_token_scope_enum.py
gitguardian/models/api_token_status_enum.py
gitguardian/models/api_token_type_enum.py
gitguardian/models/assign_incident_request.py
gitguardian/models/audit_log.py
gitguardian/models/audit_log_action_type_enum.py
gitguardian/models/base.py
gitguardian/models/compute_sca_files_ok_response.py
gitguardian/models/create_honeytoken_label_request.py
gitguardian/models/create_honeytoken_note_request.py
gitguardian/models/create_honeytoken_request.py
gitguardian/models/create_honeytoken_with_context_request.py
gitguardian/models/create_incident_note_request.py
gitguardian/models/create_invitations_request.py
gitguardian/models/create_team_invitations_request.py
gitguardian/models/create_teams_request.py
gitguardian/models/dependency_type_enum.py
gitguardian/models/detector.py
gitguardian/models/detector_group.py
gitguardian/models/detector_group_type_enum.py
gitguardian/models/diff_scan_iac_request.py
gitguardian/models/document.py
gitguardian/models/entities_with_incidents.py
gitguardian/models/exposed_vulnerability_output_schema.py
gitguardian/models/grant_access_incident_request.py
gitguardian/models/health_check_ok_response.py
gitguardian/models/hmsl_source_type_enum.py
gitguardian/models/honey_token_event.py
gitguardian/models/honey_token_event_tag.py
gitguardian/models/honey_token_label.py
gitguardian/models/honey_token_note.py
gitguardian/models/honey_token_source.py
gitguardian/models/honey_token_with_context.py
gitguardian/models/honeytoken.py
gitguardian/models/iac_diff_scan_result.py
gitguardian/models/iac_scan_result.py
gitguardian/models/iac_scan_tar_parameters.py
gitguardian/models/iac_status_enum.py
gitguardian/models/ignore_incident_request.py
gitguardian/models/incident.py
gitguardian_client-1.0.0.dist-info/LICENSE
gitguardian_client-1.0.0.dist-info/METADATA
gitguardian_client-1.0.0.dist-info/WHEEL
gitguardian_client-1.0.0.dist-info/top_level.txt
gitguardian_client-1.0.0.dist-info/RECORD
