Metadata-Version: 2.1
Name: gitguardian-client
Version: 1.0.0
Summary: Gitguardian api client
License: MIT
Requires-Python: >=3.7
License-File: LICENSE
Requires-Dist: requests >=2.31.0
